info_gtk/__init__.py
info_gtk/__main__.py
info_gtk/data_individu/__init__.py
info_gtk/data_individu/data_individu.py
info_gtk/data_individu/ijazah_terakhir.py
info_gtk/data_individu/jam_mengajar.py
info_gtk/data_individu/sekolah_induk.py
info_gtk/data_individu/status_kepegawaian.py
info_gtk/data_individu/tugas_tambahan.py
info_gtk/info_gtk.py
info_gtk/kelulusan_sertifikasi.py
info_gtk/main.py
info_gtk/profile.py
info_gtk/realisasi_sktp.py
info_gtk/rombongan_belajar.py
info_gtk/sktp.py
info_gtk/status_nuptk.py
info_gtk/table_data.py
info_gtk/verivikasi_data_tunjangan.py
info_gtk/version.py
info_gtk-0.4.0.dist-info/LICENSE
info_gtk-0.4.0.dist-info/WHEEL
info_gtk-0.4.0.dist-info/METADATA
info_gtk-0.4.0.dist-info/RECORD
